kubernetesapiuse.py
policytester.py
shell.py
policytester/DebugContainerSpec.py
policytester/PolicyTester.py
policytester/PolicyTests.py
policytester/SafeLineLoader.py
policytester/TestReport.py
policytester/__init__.py
policytester/__main__.py
policytester/kubernetes.py
policytester-0.1.4.dist-info/LICENSE
policytester-0.1.4.dist-info/METADATA
policytester-0.1.4.dist-info/WHEEL
policytester-0.1.4.dist-info/entry_points.txt
policytester-0.1.4.dist-info/top_level.txt
policytester-0.1.4.dist-info/RECORD
