Metadata-Version: 2.1
Name: policytester
Version: 0.1.4
Summary: Test kubernetes network policies
Author-email: Erik Brakkee <erik@brakkee.org>
License: 
Project-URL: Homepage, https://github.com/ErikEngerd/policytester
Project-URL: source, https://github.com/ErikEngerd/policytester.git
Project-URL: documentation, https://github.com/ErikEngerd/policytester#readme
Keywords: kubernetes,network,policy,network policy
Classifier: License :: OSI Approved :: Apache Software License
Classifier: Programming Language :: Python
Classifier: Programming Language :: Python :: 3
Classifier: Topic :: Software Development :: Testing
Classifier: Topic :: System :: Networking
Classifier: Topic :: System :: Networking :: Firewalls
Requires-Python: >=3.8
License-File: LICENSE
Requires-Dist: kubernetes (>=23.6.0)
Requires-Dist: cerberus (>=1.3.4)
Requires-Dist: pyyaml (>=6.0)
Requires-Dist: attrdict (>=2.0.1)
Requires-Dist: tomli ; python_version < "3.11"
Provides-Extra: dev
Requires-Dist: black ; extra == 'dev'
Requires-Dist: bumpver ; extra == 'dev'
Requires-Dist: isort ; extra == 'dev'
Requires-Dist: pip-tools ; extra == 'dev'
Requires-Dist: pytest ; extra == 'dev'
